NeuralNMF/__init__.py
NeuralNMF/loss.py
NeuralNMF/lsqnonneg_module.py
NeuralNMF/model.py
NeuralNMF/news_group_loading.py
NeuralNMF/train.py
NeuralNMF/writer.py
NeuralNMF-1.0.0.dist-info/LICENSE
NeuralNMF-1.0.0.dist-info/METADATA
NeuralNMF-1.0.0.dist-info/WHEEL
NeuralNMF-1.0.0.dist-info/top_level.txt
NeuralNMF-1.0.0.dist-info/RECORD
