Metadata-Version: 2.1
Name: NeuralNMF
Version: 1.0.0
Summary: UNKNOWN
Home-page: https://github.com/jvendrow/NeuralNMF
Author: Joshua Vendrow
Author-email: jvendrow@ucla.edu
License: MIT
Keywords: neural nmf
Platform: UNKNOWN
Classifier: Development Status :: 2 - Pre-Alpha
Classifier: Intended Audience :: Science/Research 
Classifier: License :: OSI Approved :: MIT License
Classifier: Natural Language :: English
Classifier: Programming Language :: Python
Classifier: Programming Language :: Python :: 3
Classifier: Programming Language :: Python :: 3 :: Only
Classifier: Programming Language :: Python :: 3.5
Classifier: Programming Language :: Python :: 3.6
Classifier: Programming Language :: Python :: 3.7
Classifier: Programming Language :: Python :: 3.8
Classifier: Topic :: Scientific/Engineering
Requires-Dist: torch
Requires-Dist: matplotlib
Requires-Dist: scipy
Requires-Dist: numpy
Requires-Dist: fnnls
Requires-Dist: tqdm
